README.md
setup.py
pg_saga.egg-info/PKG-INFO
pg_saga.egg-info/SOURCES.txt
pg_saga.egg-info/dependency_links.txt
pg_saga.egg-info/top_level.txt
src/__init__.py
src/active_record.py
src/conftest.py
src/dal.py
src/database.py
src/logger.py
src/saga.py
src/stream_utils.py