Metadata-Version: 2.1
Name: pg-saga
Version: 0.1.1
Summary: A minimalist's saga workflow
Home-page: https://github.com/z-george-ma/saga
Author: George Ma
Author-email: z.george.ma@gmail.com
License: UNKNOWN
Platform: UNKNOWN
Classifier: Programming Language :: Python :: 3
Classifier: License :: OSI Approved :: MIT License
Classifier: Operating System :: OS Independent
